MANIFEST.in
README.md
setup.py
MindYourNeighbors.egg-info/PKG-INFO
MindYourNeighbors.egg-info/SOURCES.txt
MindYourNeighbors.egg-info/dependency_links.txt
MindYourNeighbors.egg-info/requires.txt
MindYourNeighbors.egg-info/top_level.txt
data/mind-your-neighbors.service
src/myn
src/mind_your_neighbors/__init__.py
src/mind_your_neighbors/cache.py
src/mind_your_neighbors/commands.py
src/mind_your_neighbors/const.py
src/mind_your_neighbors/main.py
src/mind_your_neighbors/utils.py