Metadata-Version: 1.1
Name: MindYourNeighbors
Version: 1.0.0
Summary: IP Neighbors table watching script
Home-page: https://github.com/jaesivsm/MindYourNeighbors
Author: François Schmidts
Author-email: francois@schmidts.fr
License: GPLv3
Keywords: ip-neigh arp
Platform: UNKNOWN
Classifier: Intended Audience :: System Administrators
Classifier: Programming Language :: Python :: 3
Classifier: License :: OSI Approved :: Apache Software License
Classifier: Operating System :: POSIX :: Linux
Classifier: Development Status :: 4 - Beta
Classifier: Topic :: System :: Networking :: Monitoring :: Hardware Watchdog
Classifier: Topic :: System :: Networking
